cashew/__init__.py
cashew/exceptions.py
cashew/plugin.py
example/__init__.py
example/classes.py
example/classes1.py
example/classes2.py
example/usage1.py
example/usage2.py
example/utils.py
cashew-0.4.1.dist-info/LICENSE
cashew-0.4.1.dist-info/METADATA
cashew-0.4.1.dist-info/WHEEL
cashew-0.4.1.dist-info/top_level.txt
cashew-0.4.1.dist-info/RECORD
