Metadata-Version: 1.1
Name: cashew
Version: 0.4.1
Summary: Plugin System
Home-page: http://dexy.github.io/cashew/
Author: Ana Nelson
Author-email: ana@ananelson.com
License: UNKNOWN
Platform: UNKNOWN
Classifier: License :: OSI Approved :: MIT License
